{
  "users": [
    {
      "id": "1",
      "name": "Prashant"
    },
    {
      "id": "f747",
      "name": "Delia Dooley"
    },
    {
      "id": "20f8",
      "name": "Juana Altenwerth"
    }
  ],
  "albums": [
    {
      "id": "6020",
      "title": "Gorgeous Metal Chair",
      "userId": "f747"
    },
    {
      "id": "d02e",
      "title": "Incredible Frozen Shoes",
      "userId": "1"
    },
    {
      "id": "2a52",
      "title": "Practical Cotton Table",
      "userId": "f747"
    },
    {
      "id": "8153",
      "title": "Incredible Plastic Sausages",
      "userId": "20f8"
    }
  ],
  "photos": [
    {
      "id": "50fa",
      "albumId": "6020",
      "url": "https://loremflickr.com/150/150/abstract?lock=41915"
    }
  ]
}